{
    "timestamp": "16:40:47",
    "top15": [
        {
            "rank": 1,
            "symbol": "BGIJ26",
            "score": 100.0,
            "direction": "\u2191 LONG",
            "rsi": 44.5,
            "atr_pct": 0.21,
            "price": 336.8,
            "sector": "FUTUROS",
            "status": "\u2714\ufe0f ABERTO"
        },
        {
            "rank": 2,
            "symbol": "DIH26",
            "score": 100.0,
            "direction": "\u2191 LONG",
            "rsi": 67.7,
            "atr_pct": 0.04,
            "price": 14.75,
            "sector": "OUTROS",
            "status": "\u2714\ufe0f ABERTO"
        },
        {
            "rank": 3,
            "symbol": "ICFK26",
            "score": 80.0,
            "direction": "\u2191 LONG",
            "rsi": 78.8,
            "atr_pct": 0.59,
            "price": 398.5,
            "sector": "FUTUROS",
            "status": "\u2714\ufe0f ABERTO"
        },
        {
            "rank": 4,
            "symbol": "BGIH26",
            "score": 80.0,
            "direction": "\u2191 LONG",
            "rsi": 62.8,
            "atr_pct": 0.15,
            "price": 344.05,
            "sector": "OUTROS",
            "status": "\u2714\ufe0f ABERTO"
        },
        {
            "rank": 5,
            "symbol": "INDJ26",
            "score": 80.0,
            "direction": "\u2191 LONG",
            "rsi": 56.1,
            "atr_pct": 0.31,
            "price": 182465.0,
            "sector": "FUTUROS",
            "status": "\u2714\ufe0f ABERTO"
        },
        {
            "rank": 6,
            "symbol": "WIH26",
            "score": 80.0,
            "direction": "\u2191 LONG",
            "rsi": 55.0,
            "atr_pct": 0.34,
            "price": 182445.0,
            "sector": "OUTROS",
            "status": "\u2714\ufe0f ABERTO"
        },
        {
            "rank": 7,
            "symbol": "CCMU27",
            "score": 80.0,
            "direction": "\u2191 LONG",
            "rsi": 57.5,
            "atr_pct": 1.87,
            "price": 75.0,
            "sector": "FUTUROS",
            "status": "\u2714\ufe0f ABERTO"
        },
        {
            "rank": 8,
            "symbol": "CCMH26",
            "score": 75.0,
            "direction": "\u2191 LONG",
            "rsi": 43.3,
            "atr_pct": 0.14,
            "price": 73.51,
            "sector": "OUTROS",
            "status": "\u2714\ufe0f ABERTO"
        },
        {
            "rank": 9,
            "symbol": "WINJ26",
            "score": 60.0,
            "direction": "\u2191 LONG",
            "rsi": 55.7,
            "atr_pct": 0.34,
            "price": 182475.0,
            "sector": "FUTUROS",
            "status": "\u2714\ufe0f ABERTO"
        },
        {
            "rank": 10,
            "symbol": "WINM26",
            "score": 55.0,
            "direction": "\u2191 LONG",
            "rsi": 53.8,
            "atr_pct": 0.3,
            "price": 186320.0,
            "sector": "OUTROS",
            "status": "\u2714\ufe0f ABERTO"
        },
        {
            "rank": 11,
            "symbol": "DOLJ26",
            "score": 45.0,
            "direction": "\u2193 SHORT",
            "rsi": 37.9,
            "atr_pct": 0.24,
            "price": 5287.5,
            "sector": "FUTUROS",
            "status": "\u23f8\ufe0f AGUARDANDO"
        },
        {
            "rank": 12,
            "symbol": "BITH26",
            "score": 45.0,
            "direction": "\u2193 SHORT",
            "rsi": 39.8,
            "atr_pct": 0.51,
            "price": 360620.0,
            "sector": "FUTUROS",
            "status": "\u23f8\ufe0f AGUARDANDO"
        },
        {
            "rank": 13,
            "symbol": "WSPH26",
            "score": 45.0,
            "direction": "\u2193 SHORT",
            "rsi": 51.9,
            "atr_pct": 0.26,
            "price": 6764.25,
            "sector": "OUTROS",
            "status": "\u23f8\ufe0f AGUARDANDO"
        },
        {
            "rank": 14,
            "symbol": "WDOK26",
            "score": 45.0,
            "direction": "\u2193 SHORT",
            "rsi": 32.7,
            "atr_pct": 0.2,
            "price": 5315.0,
            "sector": "OUTROS",
            "status": "\u23f8\ufe0f AGUARDANDO"
        },
        {
            "rank": 15,
            "symbol": "BGIX26",
            "score": 25.0,
            "direction": "\u2013",
            "rsi": 55.8,
            "atr_pct": 0.88,
            "price": 345.2,
            "sector": "OUTROS",
            "status": "\u23f8\ufe0f AGUARDANDO"
        }
    ],
    "indicators": {
        "DOLJ26": {
            "symbol": "DOLJ26",
            "ema_fast": 5293.830405410274,
            "ema_slow": 5301.213211931425,
            "rsi": 37.90849673202615,
            "adx": 15.013505898523718,
            "adx_slope": 4.0367,
            "atr": 12.755720278990767,
            "atr_pct": 0.241,
            "atr_real": 0.241,
            "atr_zscore": 1.06,
            "momentum": -0.003111,
            "volume_ratio": 2.15,
            "vol_breakout": 0,
            "vwap": 5309.016065514177,
            "vwap_std": 14.143363186393193,
            "vwap_upper_2sd": 5337.302791886964,
            "vwap_lower_2sd": 5280.7293391413905,
            "obv": -1275.0,
            "obv_trend_up": 0,
            "spread_points": 1000.0,
            "spread_nominal": 1.0,
            "spread_pct": 0.0189,
            "close": 5287.5,
            "macro_trend_ok": 0,
            "tick_size": 0.001,
            "params": {},
            "error": null,
            "candle_time": 1772814600.0,
            "score_log": {
                "EMA_COUNTER_TREND": -20,
                "RSI_HEALTHY": 20,
                "ADX_OK": 20,
                "VOLUME_OK": 25
            },
            "score": 45.0,
            "direction": "\u2193 SHORT",
            "sector": "FUTUROS"
        },
        "CCMH26": {
            "symbol": "CCMH26",
            "ema_fast": 73.38424957922166,
            "ema_slow": 73.3772654612897,
            "rsi": 43.26923076923079,
            "adx": 15.634038400385187,
            "adx_slope": -4.6283,
            "atr": 0.10356038221513103,
            "atr_pct": 0.141,
            "atr_real": 0.141,
            "atr_zscore": -0.34,
            "momentum": 0.001362,
            "volume_ratio": 0.2,
            "vol_breakout": 0,
            "vwap": null,
            "vwap_std": null,
            "vwap_upper_2sd": null,
            "vwap_lower_2sd": null,
            "obv": -95.0,
            "obv_trend_up": 0,
            "spread_points": 0,
            "spread_nominal": 0,
            "spread_pct": 0,
            "close": 73.51,
            "macro_trend_ok": 0,
            "tick_size": 0.01,
            "params": {},
            "error": null,
            "candle_time": 1757088900.0,
            "score_log": {
                "EMA_TREND_OK": 35,
                "RSI_HEALTHY": 20,
                "ADX_OK": 20
            },
            "score": 75.0,
            "direction": "\u2191 LONG",
            "sector": "Elite"
        },
        "ICFK26": {
            "symbol": "ICFK26",
            "ema_fast": 394.2330780371869,
            "ema_slow": 388.78998799039573,
            "rsi": 78.83008356545966,
            "adx": 40.20974534135425,
            "adx_slope": 3.7472,
            "atr": 2.3572934471224585,
            "atr_pct": 0.592,
            "atr_real": 0.592,
            "atr_zscore": -0.44,
            "momentum": 0.029716,
            "volume_ratio": 0.42,
            "vol_breakout": 0,
            "vwap": 394.47159090909093,
            "vwap_std": 3.808491540295192,
            "vwap_upper_2sd": 402.0885739896813,
            "vwap_lower_2sd": 386.85460782850055,
            "obv": 151.0,
            "obv_trend_up": 1,
            "spread_points": 0,
            "spread_nominal": 0,
            "spread_pct": 0,
            "close": 398.5,
            "macro_trend_ok": 0,
            "tick_size": 0.01,
            "params": {},
            "error": null,
            "candle_time": 1772812800.0,
            "score_log": {
                "EMA_TREND_OK": 35,
                "ADX_OK": 20,
                "VOLUME_OK": 25
            },
            "score": 80.0,
            "direction": "\u2191 LONG",
            "sector": "FUTUROS"
        },
        "BGIH26": {
            "symbol": "BGIH26",
            "ema_fast": 343.4422894201612,
            "ema_slow": 343.22848082311987,
            "rsi": 62.82051282051252,
            "adx": 14.207726085228947,
            "adx_slope": 0.0581,
            "atr": 0.5226753302499207,
            "atr_pct": 0.152,
            "atr_real": 0.152,
            "atr_zscore": -0.15,
            "momentum": 0.002331,
            "volume_ratio": 1.74,
            "vol_breakout": 0,
            "vwap": 343.0921068214116,
            "vwap_std": 0.5947416586489859,
            "vwap_upper_2sd": 344.2815901387096,
            "vwap_lower_2sd": 341.90262350411365,
            "obv": -3219.0,
            "obv_trend_up": 1,
            "spread_points": 55.0,
            "spread_nominal": 0.55,
            "spread_pct": 0.1599,
            "close": 344.05,
            "macro_trend_ok": 0,
            "tick_size": 0.01,
            "params": {},
            "error": null,
            "candle_time": 1772813700.0,
            "score_log": {
                "EMA_TREND_OK": 35,
                "RSI_HEALTHY": 20,
                "VOLUME_OK": 25
            },
            "score": 80.0,
            "direction": "\u2191 LONG",
            "sector": "Elite"
        },
        "BGIX26": {
            "symbol": "BGIX26",
            "ema_fast": 342.3949350182325,
            "ema_slow": 342.43798434079207,
            "rsi": 55.809523809523796,
            "adx": 6.871565560210065,
            "adx_slope": -0.3229,
            "atr": 3.051457981491123,
            "atr_pct": 0.884,
            "atr_real": 0.884,
            "atr_zscore": -1.05,
            "momentum": 0.0,
            "volume_ratio": 3.0,
            "vol_breakout": 0,
            "vwap": 343.6243779620853,
            "vwap_std": 2.0110371104015634,
            "vwap_upper_2sd": 347.6464521828884,
            "vwap_lower_2sd": 339.6023037412822,
            "obv": 1304.0,
            "obv_trend_up": 1,
            "spread_points": 175.0,
            "spread_nominal": 1.75,
            "spread_pct": 0.507,
            "close": 345.2,
            "macro_trend_ok": 0,
            "tick_size": 0.01,
            "params": {},
            "error": null,
            "candle_time": 1772813700.0,
            "score_log": {
                "EMA_COUNTER_TREND": -20,
                "RSI_HEALTHY": 20,
                "VOLUME_OK": 25
            },
            "score": 25.0,
            "direction": "\u2013",
            "sector": "Elite"
        },
        "WINM26": {
            "symbol": "WINM26",
            "ema_fast": 186335.65948824465,
            "ema_slow": 186315.69625923928,
            "rsi": 53.81944444444444,
            "adx": 20.061572691879377,
            "adx_slope": -6.8028,
            "atr": 565.4324641361171,
            "atr_pct": 0.303,
            "atr_real": 0.303,
            "atr_zscore": 0.53,
            "momentum": 0.000859,
            "volume_ratio": 0.23,
            "vol_breakout": 0,
            "vwap": 186024.78865511794,
            "vwap_std": 432.3861819677555,
            "vwap_upper_2sd": 186889.56101905345,
            "vwap_lower_2sd": 185160.01629118243,
            "obv": -10617.0,
            "obv_trend_up": 1,
            "spread_points": 20.0,
            "spread_nominal": 20.0,
            "spread_pct": 0.0107,
            "close": 186320.0,
            "macro_trend_ok": 0,
            "tick_size": 1.0,
            "params": {},
            "error": null,
            "candle_time": 1772814600.0,
            "score_log": {
                "EMA_TREND_OK": 35,
                "RSI_HEALTHY": 20,
                "ADX_OK": 20
            },
            "score": 55.0,
            "direction": "\u2191 LONG",
            "sector": "Elite"
        },
        "BGIJ26": {
            "symbol": "BGIJ26",
            "ema_fast": 337.22584751127414,
            "ema_slow": 337.0653359182098,
            "rsi": 44.54545454545469,
            "adx": 23.23512999273969,
            "adx_slope": 6.0884,
            "atr": 0.7206787047560758,
            "atr_pct": 0.214,
            "atr_real": 0.214,
            "atr_zscore": 0.27,
            "momentum": -0.000593,
            "volume_ratio": 2.46,
            "vol_breakout": 1,
            "vwap": 336.7255894590846,
            "vwap_std": 0.6570323431917238,
            "vwap_upper_2sd": 338.03965414546803,
            "vwap_lower_2sd": 335.4115247727011,
            "obv": -2145.0,
            "obv_trend_up": 0,
            "spread_points": 40.0,
            "spread_nominal": 0.4,
            "spread_pct": 0.1189,
            "close": 336.8,
            "macro_trend_ok": 0,
            "tick_size": 0.01,
            "params": {},
            "error": null,
            "candle_time": 1772813700.0,
            "score_log": {
                "EMA_TREND_OK": 35,
                "RSI_HEALTHY": 20,
                "ADX_OK": 20,
                "VOLUME_OK": 25
            },
            "score": 100.0,
            "direction": "\u2191 LONG",
            "sector": "FUTUROS"
        },
        "INDJ26": {
            "symbol": "INDJ26",
            "ema_fast": 182415.19431765805,
            "ema_slow": 182391.23127952134,
            "rsi": 56.06694560669456,
            "adx": 15.232783371979693,
            "adx_slope": -5.4483,
            "atr": 572.8313166451272,
            "atr_pct": 0.314,
            "atr_real": 0.314,
            "atr_zscore": 0.63,
            "momentum": 0.001509,
            "volume_ratio": 0.71,
            "vol_breakout": 0,
            "vwap": 182401.7002928734,
            "vwap_std": 423.2014615089598,
            "vwap_upper_2sd": 183248.10321589131,
            "vwap_lower_2sd": 181555.29736985549,
            "obv": -15627.0,
            "obv_trend_up": 1,
            "spread_points": 35.0,
            "spread_nominal": 35.0,
            "spread_pct": 0.0192,
            "close": 182465.0,
            "macro_trend_ok": 0,
            "tick_size": 1.0,
            "params": {},
            "error": null,
            "candle_time": 1772814600.0,
            "score_log": {
                "EMA_TREND_OK": 35,
                "RSI_HEALTHY": 20,
                "ADX_OK": 20,
                "VOLUME_OK": 25
            },
            "score": 80.0,
            "direction": "\u2191 LONG",
            "sector": "FUTUROS"
        },
        "WIH26": {
            "symbol": "WIH26",
            "ema_fast": 182405.26456686942,
            "ema_slow": 182382.41362512694,
            "rsi": 55.04761904761904,
            "adx": 14.30977121254937,
            "adx_slope": -5.375,
            "atr": 615.0612737721248,
            "atr_pct": 0.337,
            "atr_real": 0.337,
            "atr_zscore": 0.85,
            "momentum": 0.001207,
            "volume_ratio": 0.73,
            "vol_breakout": 0,
            "vwap": 182216.55403861302,
            "vwap_std": 425.15993924275114,
            "vwap_upper_2sd": 183066.8739170985,
            "vwap_lower_2sd": 181366.23416012753,
            "obv": -4210680.0,
            "obv_trend_up": 1,
            "spread_points": 0,
            "spread_nominal": 0,
            "spread_pct": 0,
            "close": 182445.0,
            "macro_trend_ok": 0,
            "tick_size": 0.0,
            "params": {},
            "error": null,
            "candle_time": 1772814600.0,
            "score_log": {
                "EMA_TREND_OK": 35,
                "RSI_HEALTHY": 20,
                "VOLUME_OK": 25
            },
            "score": 80.0,
            "direction": "\u2191 LONG",
            "sector": "Elite"
        },
        "BITH26": {
            "symbol": "BITH26",
            "ema_fast": 362025.4941078948,
            "ema_slow": 364182.1722080589,
            "rsi": 39.77272727272727,
            "adx": 51.191256164424125,
            "adx_slope": 0.4427,
            "atr": 1825.1683811248843,
            "atr_pct": 0.506,
            "atr_real": 0.506,
            "atr_zscore": 0.19,
            "momentum": -0.007431,
            "volume_ratio": 1.05,
            "vol_breakout": 0,
            "vwap": 366122.015070919,
            "vwap_std": 3628.9683921496,
            "vwap_upper_2sd": 373379.9518552182,
            "vwap_lower_2sd": 358864.0782866198,
            "obv": -12925.0,
            "obv_trend_up": 0,
            "spread_points": 6000.0,
            "spread_nominal": 60.0,
            "spread_pct": 0.0166,
            "close": 360620.0,
            "macro_trend_ok": 0,
            "tick_size": 0.01,
            "params": {},
            "error": null,
            "candle_time": 1772814600.0,
            "score_log": {
                "EMA_COUNTER_TREND": -20,
                "RSI_HEALTHY": 20,
                "ADX_OK": 20,
                "VOLUME_OK": 25
            },
            "score": 45.0,
            "direction": "\u2193 SHORT",
            "sector": "FUTUROS"
        },
        "WSPH26": {
            "symbol": "WSPH26",
            "ema_fast": 6764.950836830897,
            "ema_slow": 6766.285326548451,
            "rsi": 51.86104218362282,
            "adx": 15.520457953818896,
            "adx_slope": -4.8654,
            "atr": 17.313668228742376,
            "atr_pct": 0.256,
            "atr_real": 0.256,
            "atr_zscore": 1.08,
            "momentum": 0.00074,
            "volume_ratio": 2.0,
            "vol_breakout": 0,
            "vwap": 6757.364816922555,
            "vwap_std": 14.833246997136271,
            "vwap_upper_2sd": 6787.031310916828,
            "vwap_lower_2sd": 6727.698322928282,
            "obv": 663.0,
            "obv_trend_up": 0,
            "spread_points": 50.0,
            "spread_nominal": 0.5,
            "spread_pct": 0.0074,
            "close": 6764.25,
            "macro_trend_ok": 1,
            "tick_size": 0.01,
            "params": {},
            "error": null,
            "candle_time": 1772814600.0,
            "score_log": {
                "EMA_COUNTER_TREND": -20,
                "RSI_HEALTHY": 20,
                "ADX_OK": 20,
                "VOLUME_OK": 25
            },
            "score": 45.0,
            "direction": "\u2193 SHORT",
            "sector": "Elite"
        },
        "WDOV26": {
            "symbol": "WDOV26",
            "ema_fast": 5330.886551362494,
            "ema_slow": 5340.109292683786,
            "rsi": 46.01990049751244,
            "adx": 14.322516242945685,
            "adx_slope": 0.988,
            "atr": 23.941057323048796,
            "atr_pct": 0.45,
            "atr_real": 0.45,
            "atr_zscore": -0.97,
            "momentum": -0.004868,
            "volume_ratio": 1.22,
            "vol_breakout": 0,
            "vwap": 5350.75863764045,
            "vwap_std": 24.21191625729809,
            "vwap_upper_2sd": 5399.182470155046,
            "vwap_lower_2sd": 5302.334805125854,
            "obv": -1375.0,
            "obv_trend_up": 0,
            "spread_points": 0,
            "spread_nominal": 0,
            "spread_pct": 0,
            "close": 5315.0,
            "macro_trend_ok": 0,
            "tick_size": 0.001,
            "params": {},
            "error": null,
            "candle_time": 1772814600.0,
            "score_log": {
                "EMA_COUNTER_TREND": -20,
                "RSI_HEALTHY": 20,
                "VOLUME_OK": 25
            },
            "score": 25.0,
            "direction": "\u2193 SHORT",
            "sector": "FUTUROS"
        },
        "DIH26": {
            "symbol": "DIH26",
            "ema_fast": 14.745258464137969,
            "ema_slow": 14.743305630741906,
            "rsi": 67.7419354838704,
            "adx": 25.26244918406865,
            "adx_slope": 0.0595,
            "atr": 0.006128025567345452,
            "atr_pct": 0.042,
            "atr_real": 0.042,
            "atr_zscore": 1.11,
            "momentum": 0.001018,
            "volume_ratio": 2.05,
            "vol_breakout": 0,
            "vwap": 14.742359451966438,
            "vwap_std": 0.00435252161906675,
            "vwap_upper_2sd": 14.751064495204572,
            "vwap_lower_2sd": 14.733654408728304,
            "obv": 9593.0,
            "obv_trend_up": 1,
            "spread_points": 0,
            "spread_nominal": 0,
            "spread_pct": 0,
            "close": 14.753,
            "macro_trend_ok": 0,
            "tick_size": 0.0,
            "params": {},
            "error": null,
            "candle_time": 1772814600.0,
            "score_log": {
                "EMA_TREND_OK": 35,
                "RSI_HEALTHY": 20,
                "ADX_OK": 20,
                "VOLUME_OK": 25
            },
            "score": 100.0,
            "direction": "\u2191 LONG",
            "sector": "Elite"
        },
        "WINJ26": {
            "symbol": "WINJ26",
            "ema_fast": 182411.26456686942,
            "ema_slow": 182385.1408978542,
            "rsi": 55.6840077071291,
            "adx": 14.30977121254937,
            "adx_slope": -5.375,
            "atr": 615.0612737721248,
            "atr_pct": 0.337,
            "atr_real": 0.337,
            "atr_zscore": 0.85,
            "momentum": 0.001372,
            "volume_ratio": 0.73,
            "vol_breakout": 0,
            "vwap": 182217.09370559515,
            "vwap_std": 425.48074560830827,
            "vwap_upper_2sd": 183068.05519681177,
            "vwap_lower_2sd": 181366.13221437854,
            "obv": -4210680.0,
            "obv_trend_up": 1,
            "spread_points": 5.0,
            "spread_nominal": 5.0,
            "spread_pct": 0.0027,
            "close": 182475.0,
            "macro_trend_ok": 0,
            "tick_size": 1.0,
            "params": {},
            "error": null,
            "candle_time": 1772814600.0,
            "score_log": {
                "EMA_TREND_OK": 35,
                "RSI_HEALTHY": 20,
                "VOLUME_OK": 25
            },
            "score": 60.0,
            "direction": "\u2191 LONG",
            "sector": "FUTUROS"
        },
        "ICFH26": {
            "symbol": "ICFH26",
            "ema_fast": 454.7399523479965,
            "ema_slow": 455.5485577101762,
            "rsi": 51.851851851851805,
            "adx": 10.483363952802266,
            "adx_slope": -0.4738,
            "atr": 2.369546010013011,
            "atr_pct": 0.521,
            "atr_real": 0.521,
            "atr_zscore": -1.07,
            "momentum": -0.012918,
            "volume_ratio": 0.3,
            "vol_breakout": 0,
            "vwap": null,
            "vwap_std": null,
            "vwap_upper_2sd": null,
            "vwap_lower_2sd": null,
            "obv": 76.0,
            "obv_trend_up": 0,
            "spread_points": 0,
            "spread_nominal": 0,
            "spread_pct": 0,
            "close": 454.65,
            "macro_trend_ok": 0,
            "tick_size": 0.01,
            "params": {},
            "error": null,
            "candle_time": 1757081700.0,
            "score_log": {
                "EMA_COUNTER_TREND": -20,
                "RSI_HEALTHY": 20
            },
            "score": 0.0,
            "direction": "\u2013",
            "sector": "Elite"
        },
        "WDOK26": {
            "symbol": "WDOK26",
            "ema_fast": 5325.940781415872,
            "ema_slow": 5333.944762843359,
            "rsi": 32.66666666666667,
            "adx": 15.60537477126444,
            "adx_slope": 3.6385,
            "atr": 10.610047380092496,
            "atr_pct": 0.2,
            "atr_real": 0.2,
            "atr_zscore": 0.3,
            "momentum": -0.004215,
            "volume_ratio": 0.81,
            "vol_breakout": 0,
            "vwap": 5349.211217008798,
            "vwap_std": 14.364233010720852,
            "vwap_upper_2sd": 5377.939683030239,
            "vwap_lower_2sd": 5320.482750987356,
            "obv": 1312.0,
            "obv_trend_up": 0,
            "spread_points": 1000.0,
            "spread_nominal": 1.0,
            "spread_pct": 0.0188,
            "close": 5315.0,
            "macro_trend_ok": 0,
            "tick_size": 0.001,
            "params": {},
            "error": null,
            "candle_time": 1772814600.0,
            "score_log": {
                "EMA_COUNTER_TREND": -20,
                "RSI_HEALTHY": 20,
                "ADX_OK": 20,
                "VOLUME_OK": 25
            },
            "score": 45.0,
            "direction": "\u2193 SHORT",
            "sector": "Elite"
        },
        "CCMK26": {
            "symbol": "CCMK26",
            "ema_fast": 71.96557245703218,
            "ema_slow": 71.99524825862039,
            "rsi": 39.86486486486519,
            "adx": 11.10130380082108,
            "adx_slope": -1.1376,
            "atr": 0.1273180181535999,
            "atr_pct": 0.177,
            "atr_real": 0.177,
            "atr_zscore": -0.86,
            "momentum": -0.000556,
            "volume_ratio": 0.56,
            "vol_breakout": 0,
            "vwap": null,
            "vwap_std": null,
            "vwap_upper_2sd": null,
            "vwap_lower_2sd": null,
            "obv": -865.0,
            "obv_trend_up": 1,
            "spread_points": 0,
            "spread_nominal": 0,
            "spread_pct": 0,
            "close": 71.86,
            "macro_trend_ok": 0,
            "tick_size": 0.01,
            "params": {},
            "error": null,
            "candle_time": 1757088900.0,
            "score_log": {
                "EMA_COUNTER_TREND": -20,
                "RSI_HEALTHY": 20,
                "VOLUME_OK": 25
            },
            "score": 25.0,
            "direction": "\u2193 SHORT",
            "sector": "Elite"
        },
        "WDOJ26": {
            "symbol": "WDOJ26",
            "ema_fast": 5292.368075404107,
            "ema_slow": 5300.553641167531,
            "rsi": 30.935251798561154,
            "adx": 14.5949401300146,
            "adx_slope": 3.5143,
            "atr": 13.184835893267477,
            "atr_pct": 0.25,
            "atr_real": 0.25,
            "atr_zscore": 1.14,
            "momentum": -0.004525,
            "volume_ratio": 1.19,
            "vol_breakout": 0,
            "vwap": 5312.264752531068,
            "vwap_std": 14.380289925456719,
            "vwap_upper_2sd": 5341.025332381981,
            "vwap_lower_2sd": 5283.504172680155,
            "obv": 135402.0,
            "obv_trend_up": 0,
            "spread_points": 500.0,
            "spread_nominal": 0.5,
            "spread_pct": 0.0095,
            "close": 5279.5,
            "macro_trend_ok": 0,
            "tick_size": 0.001,
            "params": {},
            "error": null,
            "candle_time": 1772814600.0,
            "score_log": {
                "EMA_COUNTER_TREND": -20,
                "RSI_HEALTHY": 20,
                "VOLUME_OK": 25
            },
            "score": 25.0,
            "direction": "\u2193 SHORT",
            "sector": "Elite"
        },
        "CCMU27": {
            "symbol": "CCMU27",
            "ema_fast": 73.58404319080864,
            "ema_slow": 73.34529935415864,
            "rsi": 57.52508361204014,
            "adx": 6.747632622958912,
            "adx_slope": -0.1333,
            "atr": 1.4008254081764042,
            "atr_pct": 1.868,
            "atr_real": 1.868,
            "atr_zscore": -0.72,
            "momentum": 0.036914,
            "volume_ratio": 0.59,
            "vol_breakout": 0,
            "vwap": 72.93100738396626,
            "vwap_std": 1.2571969896692152,
            "vwap_upper_2sd": 75.4454013633047,
            "vwap_lower_2sd": 70.41661340462782,
            "obv": -1271.0,
            "obv_trend_up": 1,
            "spread_points": 0,
            "spread_nominal": 0,
            "spread_pct": 0,
            "close": 75.0,
            "macro_trend_ok": 0,
            "tick_size": 0.01,
            "params": {},
            "error": null,
            "candle_time": 1772813700.0,
            "score_log": {
                "EMA_TREND_OK": 35,
                "RSI_HEALTHY": 20,
                "VOLUME_OK": 25
            },
            "score": 80.0,
            "direction": "\u2191 LONG",
            "sector": "FUTUROS"
        }
    }
}